ak_postmonkey-1.0b1.dist-info/DESCRIPTION.rst
ak_postmonkey-1.0b1.dist-info/METADATA
ak_postmonkey-1.0b1.dist-info/RECORD
ak_postmonkey-1.0b1.dist-info/WHEEL
ak_postmonkey-1.0b1.dist-info/metadata.json
ak_postmonkey-1.0b1.dist-info/top_level.txt
postmonkey/__init__.py
postmonkey/exceptions.py
postmonkey/tests.py
