Metadata-Version: 2.0
Name: ak-postmonkey
Version: 1.0b1
Summary: Appknox fork of Python wrapper for Mailchimp API
Home-page: http://postmonkey.readthedocs.org/
Author: Eric Rasmussen
Author-email: eric@chromaticleaves.com
License: FreeBSD
Keywords: mailchimp
Platform: UNKNOWN
Classifier: Intended Audience :: Developers
Classifier: Programming Language :: Python
Classifier: Programming Language :: Python :: 2.6
Classifier: Programming Language :: Python :: 2.7
Classifier: Programming Language :: Python :: 3.5
Requires-Dist: requests
